dotest/__init__.py
dotest/debug.py
dotest/dotest.py
dotest/generate.py
dotest/logger.py
dotest/main.py
dotest/plugin.py
dotest/report.py
dotest/tools.py
dotest-0.1.1.dist-info/entry_points.txt
dotest-0.1.1.dist-info/LICENSE
dotest-0.1.1.dist-info/WHEEL
dotest-0.1.1.dist-info/METADATA
dotest-0.1.1.dist-info/RECORD
