Metadata-Version: 2.1
Name: dotest
Version: 0.1.1
Summary: A system testing framework based on pytest
Author: pyrunner
Author-email: pyrunner@qq.com
Requires-Python: >=3.8,<4.0
Classifier: Programming Language :: Python :: 3
Classifier: Programming Language :: Python :: 3.10
Classifier: Programming Language :: Python :: 3.8
Classifier: Programming Language :: Python :: 3.9
Requires-Dist: junitparser (>=2,<3)
Requires-Dist: pytest (>=7,<8)
